django_display_ids/__init__.py
django_display_ids/admin.py
django_display_ids/apps.py
django_display_ids/conf.py
django_display_ids/contrib/__init__.py
django_display_ids/contrib/drf_spectacular/__init__.py
django_display_ids/contrib/rest_framework/__init__.py
django_display_ids/contrib/rest_framework/serializers.py
django_display_ids/contrib/rest_framework/views.py
django_display_ids/converters.py
django_display_ids/encoding.py
django_display_ids/examples.py
django_display_ids/exceptions.py
django_display_ids/managers.py
django_display_ids/models.py
django_display_ids/py.typed
django_display_ids/resolver.py
django_display_ids/strategies.py
django_display_ids/templatetags/__init__.py
django_display_ids/templatetags/display_ids.py
django_display_ids/typing.py
django_display_ids/views.py
django_display_ids-0.3.1.dist-info/WHEEL
django_display_ids-0.3.1.dist-info/METADATA
django_display_ids-0.3.1.dist-info/RECORD
