Metadata-Version: 2.3
Name: django-display-ids
Version: 0.3.1
Summary: Stripe-like prefixed IDs for Django. Works with existing UUIDs — no schema changes.
Keywords: django,stripe,uuid,base62,prefixed-id,drf,shortuuid,nanoid,ulid
License: MIT
Classifier: Development Status :: 4 - Beta
Classifier: Framework :: Django
Classifier: Framework :: Django :: 4.2
Classifier: Framework :: Django :: 5.2
Classifier: Framework :: Django :: 6.0
Classifier: License :: OSI Approved :: MIT License
Classifier: Programming Language :: Python :: 3
Classifier: Programming Language :: Python :: 3.12
Classifier: Programming Language :: Python :: 3.13
Classifier: Programming Language :: Python :: 3.14
Classifier: Typing :: Typed
Requires-Dist: django>=4.2
Requires-Python: >=3.12
Project-URL: Documentation, https://django-display-ids.readthedocs.io/
Project-URL: Repository, https://github.com/josephabrahams/django-display-ids
